primary/__init__.py
primary/main.py
primary-0.0.1.dev1.dist-info/LICENSE.txt
primary-0.0.1.dev1.dist-info/METADATA
primary-0.0.1.dev1.dist-info/WHEEL
primary-0.0.1.dev1.dist-info/entry_points.txt
primary-0.0.1.dev1.dist-info/top_level.txt
primary-0.0.1.dev1.dist-info/RECORD
